LICENSE
MANIFEST.in
README.md
setup.py
pixtalks/FaceAlign3D.py
pixtalks/FaceRecognition.py
pixtalks/Fitting.py
pixtalks/GetDepthMap.py
pixtalks/ICP.py
pixtalks/Liveness3D.py
pixtalks/__init__.py
pixtalks/__version__.py
pixtalks/blur.py
pixtalks/timer.py
pixtalks/usual_command.py
pixtalks.egg-info/PKG-INFO
pixtalks.egg-info/SOURCES.txt
pixtalks.egg-info/dependency_links.txt
pixtalks.egg-info/requires.txt
pixtalks.egg-info/top_level.txt
pixtalks/Augmentation/__init__.py
pixtalks/Augmentation/poisson.py
pixtalks/DataLoader/ImageLoader.py
pixtalks/DataLoader/MixtureDataLoader.py
pixtalks/DataLoader/MultiDataLoader.py
pixtalks/DataLoader/TensorLoader.py
pixtalks/DataLoader/__init__.py
pixtalks/Evaluate/__init__.py
pixtalks/Gradient/__init__.py
pixtalks/Metric/ArcFace.py
pixtalks/Metric/CenterLoss.py
pixtalks/Metric/Cos_Distance.py
pixtalks/Metric/__init__.py
pixtalks/Model/__init__.py
pixtalks/Model/AlignNet/Quarter.py
pixtalks/Model/AlignNet/__init__.py
pixtalks/Model/AlignNet/train.py
pixtalks/Model/AutoEndoder/__init__.py
pixtalks/Model/AutoEndoder/test.py
pixtalks/Model/AutoEndoder/train.py
pixtalks/Model/ClassifyNet/__init__.py
pixtalks/Model/ConditionalAutoEncoder/__init__.py
pixtalks/Model/ConditionalAutoEncoder/train.py
pixtalks/Model/DCGAN/__init__.py
pixtalks/Model/FRNet_v1/MobileFaceNet.py
pixtalks/Model/FRNet_v1/__init__.py
pixtalks/Model/FRNet_v2/__init__.py
pixtalks/Model/FRNet_v2/train.py
pixtalks/Model/FR_Liveness_Net/__init__.py
pixtalks/Model/FR_Liveness_Net/train.py
pixtalks/Model/KeypointNet/__init__.py
pixtalks/Model/KeypointNet/train.py
pixtalks/Model/LivenessNet/LivenessNet.py
pixtalks/Model/LivenessNet/Liveness_GAN.py
pixtalks/Model/LivenessNet/__init__.py
pixtalks/Model/LivenessNet/train.py
pixtalks/Model/StyleGAN/__init__.py
pixtalks/Model/StyleGAN/networks_stylegan.py
pixtalks/Model/VAE/__init__.py
pixtalks/Model/VAE/train.py
pixtalks/Model/mobilefacenet/MobileFaceNet_Relu.py
pixtalks/Model/mobilefacenet/__init__.py
pixtalks/ProgressBar/__init__.py
pixtalks/Random/__init__.py
pixtalks/Trainer/AutoEncoderTrainer.py
pixtalks/Trainer/ClassifyTrainer.py
pixtalks/Trainer/ConditionalAutoEncoderTrainer.py
