Metadata-Version: 2.1
Name: pixtalks
Version: 1.0.0
Summary: My short description for my project.
Home-page: https://github.com/IMath123/IMath
Author: IMath
Author-email: imatphy@gmail.com
License: MIT
Platform: UNKNOWN
Classifier: License :: OSI Approved :: MIT License
Classifier: Programming Language :: Python
Classifier: Programming Language :: Python :: 3
Classifier: Programming Language :: Python :: 3.6
Classifier: Programming Language :: Python :: Implementation :: CPython
Classifier: Programming Language :: Python :: Implementation :: PyPy
Requires-Python: >=3.6.0
